AUTHORS.rst
CONTRIBUTING.rst
HISTORY.rst
LICENSE
MANIFEST.in
README.rst
setup.cfg
setup.py
docs/Makefile
docs/authors.rst
docs/conf.py
docs/contributing.rst
docs/history.rst
docs/index.rst
docs/installation.rst
docs/make.bat
docs/readme.rst
docs/usage.rst
plugz/__init__.py
plugz/loading.py
plugz/plugz.py
plugz.egg-info/PKG-INFO
plugz.egg-info/SOURCES.txt
plugz.egg-info/dependency_links.txt
plugz.egg-info/not-zip-safe
plugz.egg-info/top_level.txt
plugz/errors/__init__.py
plugz/plugintypes/__init__.py
plugz/plugintypes/standard_plugin_type.py
tests/__init__.py
tests/test_plugz.py
tests/data/plugins/standard/invalid/plugin_one_inv.py
tests/data/plugins/standard/invalid/plugin_two_inv.py
tests/data/plugins/standard/valid/plugin_one.py
tests/data/plugins/standard/valid/plugin_two.py