Metadata-Version: 1.1
Name: plugz
Version: 0.1.2
Summary: Plugin framework that simplifies plugin support in your tools
Home-page: https://github.com/mistermatti/plugz
Author: Matti Gruener
Author-email: matti@mistermatti.com
License: BSD
Keywords: plugz
Platform: UNKNOWN
Classifier: Development Status :: 2 - Pre-Alpha
Classifier: Intended Audience :: Developers
Classifier: License :: OSI Approved :: BSD License
Classifier: Natural Language :: English
Classifier: Programming Language :: Python :: 2
Classifier: Programming Language :: Python :: 2.6
Classifier: Programming Language :: Python :: 2.7
Classifier: Programming Language :: Python :: 3
Classifier: Programming Language :: Python :: 3.3
Classifier: Programming Language :: Python :: 3.4
